rws_waterinfo/__init__.py
rws_waterinfo/rws_waterinfo.py
rws_waterinfo-0.1.1.dist-info/LICENSE
rws_waterinfo-0.1.1.dist-info/METADATA
rws_waterinfo-0.1.1.dist-info/NOTICE
rws_waterinfo-0.1.1.dist-info/WHEEL
rws_waterinfo-0.1.1.dist-info/top_level.txt
rws_waterinfo-0.1.1.dist-info/RECORD
